<?xml version="1.0" encoding="utf-8"?>
<LanguageData>
  <NamerCults.rulePack.rulesStrings.0>name-&gt;Порядок [deity]</NamerCults.rulePack.rulesStrings.0>
  <NamerCults.rulePack.rulesStrings.1>name-&gt;Церковь [ideal]</NamerCults.rulePack.rulesStrings.1>
  <NamerCults.rulePack.rulesStrings.2>name-&gt;Эзотерический орден [deity]</NamerCults.rulePack.rulesStrings.2>
  <NamerCults.rulePack.rulesStrings.3>name-&gt;Привратники [deity]</NamerCults.rulePack.rulesStrings.3>
  <NamerCults.rulePack.rulesStrings.4>name-&gt;Храм [deity]</NamerCults.rulePack.rulesStrings.4>
  <NamerCults.rulePack.rulesStrings.5>name-&gt;Дети [ideal]</NamerCults.rulePack.rulesStrings.5>
</LanguageData>